movan_rpc/__init__.py
movan_rpc/client.py
movan_rpc/client_threading.py
movan_rpc/crypto.py
movan_rpc/server.py
movan_rpc/utils.py
movan_rpc-0.1.6.dist-info/licenses/LICENSE
movan_rpc-0.1.6.dist-info/METADATA
movan_rpc-0.1.6.dist-info/WHEEL
movan_rpc-0.1.6.dist-info/top_level.txt
movan_rpc-0.1.6.dist-info/RECORD
