Metadata-Version: 2.4
Name: movan_rpc
Version: 0.1.6
Summary: 一个轻量级的 RPC（远程过程调用）框架，使用 Python 标准库实现，无需第三方依赖
Author-email: lifesize <lifesize1@qq.com>
License: MIT
Project-URL: Homepage, https://github.com/CGandGameEngineLearner/movan_rpc
Project-URL: Bug Tracker, https://github.com/CGandGameEngineLearner/movan_rpc/issues
Project-URL: Documentation, https://github.com/CGandGameEngineLearner/movan_rpc
Project-URL: Source, https://github.com/CGandGameEngineLearner/movan_rpc
Keywords: rpc,movan,remote,async,network
Classifier: Development Status :: 4 - Beta
Classifier: Intended Audience :: Developers
Classifier: License :: OSI Approved :: MIT License
Classifier: Programming Language :: Python :: 3
Classifier: Programming Language :: Python :: 3.11
Classifier: Operating System :: OS Independent
Classifier: Topic :: Software Development :: Libraries :: Python Modules
Classifier: Topic :: Internet
Requires-Python: >=3.11
License-File: LICENSE
Dynamic: license-file
